{
  "title": "背對背擁抱",
  "artist": "太合音樂 Taihe Music-精選",
  "category": "mandarin_pop",
  "duration_sec": 243.0,
  "key_offset": 0,
  "gender_variant": null,
  "youtube_url": "https://www.youtube.com/watch?v=7xgucJEqNDo",
  "youtube_title": "林俊傑 JJ Lin【背對背擁抱 Back To Back】官方完整版 MV",
  "view_count": 22033303,
  "separation_model": "htdemucs_ft",
  "files": {
    "instrumental": "instrumental.wav",
    "vocals": "vocals.wav",
    "original": "original.mp3"
  },
  "lyrics": {
    "source": "netease",
    "has_timestamps": true
  },
  "built_at": "2026-04-23T01:55:49.675875"
}